Autocallable/AutocallableSingleUnderlyingPricer.py
Autocallable/AutocallableTwoUnderlyingsPricer.py
Autocallable/__init__.py
StableGreeksInvestigationToolbox/StableGreeksInvestigationToolbox.py
StableGreeksInvestigationToolbox/__init__.py
mymontecarloopensource-0.0.3.dist-info/METADATA
mymontecarloopensource-0.0.3.dist-info/WHEEL
mymontecarloopensource-0.0.3.dist-info/top_level.txt
mymontecarloopensource-0.0.3.dist-info/RECORD
