Metadata-Version: 2.1
Name: mymontecarloopensource
Version: 0.0.3
Requires-Dist: numpy
Requires-Dist: scipy
Requires-Dist: matplotlib
